bodotokenizer/__init__.py
bodotokenizer/bodotokenizer.py
bodotokenizer/helpers.py
bodotokenizer/normalizer.py
bodotokenizer-0.1.1.dist-info/LICENSE
bodotokenizer-0.1.1.dist-info/METADATA
bodotokenizer-0.1.1.dist-info/WHEEL
bodotokenizer-0.1.1.dist-info/top_level.txt
bodotokenizer-0.1.1.dist-info/RECORD
