Metadata-Version: 2.1
Name: bodotokenizer
Version: 0.1.1
Summary: Package for Bodo Tokenizer
Home-page: https://github.com/bodonlp/bodo-tokenizer
Author: Maharaj Brahma
Author-email: mraj.brahma@gmail.com
License: MIT License        
Keywords: Bodo language,Bodo Tokenizer
Platform: UNKNOWN
Classifier: Programming Language :: Python :: 3
Classifier: License :: OSI Approved :: MIT License
Classifier: Operating System :: OS Independent
Requires-Python: >=3.6
License-File: LICENSE
